sendcyh/__init__.py
sendcyh-0.1.1.dist-info/licenses/LICENSE
sendcyh-0.1.1.dist-info/METADATA
sendcyh-0.1.1.dist-info/WHEEL
sendcyh-0.1.1.dist-info/top_level.txt
sendcyh-0.1.1.dist-info/RECORD
