Metadata-Version: 2.4
Name: sendcyh
Version: 0.1.1
Summary: Send iOS Bark notifications easily to cyh.
Author: cyh
Author-email: isyuhaochen@gmail.com
Classifier: Programming Language :: Python :: 3
Classifier: Operating System :: OS Independent
Requires-Python: >=3.6
License-File: LICENSE
Requires-Dist: requests
Dynamic: author
Dynamic: author-email
Dynamic: classifier
Dynamic: license-file
Dynamic: requires-dist
Dynamic: requires-python
Dynamic: summary
